{
    "russia": 0,
    "ukraine": 1,
    "kazakhstan": 2,
    "china": 3,
    "philippines": 4,
    "indonesia": 6,
    "malaysia": 7,
    "kenya": 8,
    "tanzania": 9,
    "vietnam": 10,
    "kyrgyzstan": 11,
    "usa": 12,
    "israel": 13,
    "hongkong": 14,
    "poland": 15,
    "england": 16,
    "madagascar": 17,
    "congo": 18,
    "nigeria": 19,
    "macau": 20,
    "egypt": 21,
    "india": 22,
    "ireland": 23,
    "laos": 25,
    "haiti": 26,
    "ivorycoast": 27,
    "gambia": 28,
    "serbia": 29,
    "southafrica": 31,
    "romania": 32,
    "colombia": 33,
    "estonia": 34,
    "azerbaijan": 35,
    "canada": 36,
    "morocco": 37,
    "ghana": 38,
    "argentina": 39,
    "uzbekistan": 40,
    "cameroon": 41,
    "chad": 42,
    "germany": 43,
    "lithuania": 44,
    "croatia": 45,
    "sweden": 46,
    "netherlands": 48,
    "latvia": 49,
    "austria": 50,
    "belarus": 51,
    "thailand": 52,
    "saudiarabia": 53,
    "mexico": 54,
    "taiwan": 55,
    "spain": 56,
    "algeria": 58,
    "slovenia": 59,
    "bangladesh": 60,
    "senegal": 61,
    "turkey": 62,
    "czechia": 63,
    "srilanka": 64,
    "peru": 65,
    "pakistan": 66,
    "newzealand": 67,
    "venezuela": 70,
    "ethiopia": 71,
    "mongolia": 72,
    "brazil": 73,
    "afghanistan": 74,
    "uganda": 75,
    "angola": 76,
    "cyprus": 77,
    "france": 78,
    "papuanewguinea": 79,
    "mozambique": 80,
    "nepal": 81,
    "belgium": 82,
    "bulgaria": 83,
    "hungary": 84,
    "moldova": 85,
    "italy": 86,
    "paraguay": 87,
    "honduras": 88,
    "tunisia": 89,
    "nicaragua": 90,
    "easttimor": 91,
    "bolivia": 92,
    "costarica": 93,
    "guatemala": 94,
    "zimbabwe": 96,
    "puertorico": 97,
    "togo": 99,
    "kuwait": 100,
    "salvador": 101,
    "jamaica": 103,
    "trinidadandtobago": 104,
    "ecuador": 105,
    "swaziland": 106,
    "oman": 107,
    "bosniaandherzegovina": 108,
    "dominicanrepublic": 109,
    "panama": 112,
    "mauritania": 114,
    "sierraleone": 115,
    "jordan": 116,
    "portugal": 117,
    "barbados": 118,
    "burundi": 119,
    "benin": 120,
    "botswana": 123,
    "georgia": 128,
    "greece": 129,
    "guinea-bissau": 130,
    "guyana": 131,
    "saintkittsandnevis": 134,
    "liberia": 135,
    "lesotho": 136,
    "malawi": 137,
    "namibia": 138,
    "rwanda": 140,
    "slovakia": 141,
    "suriname": 142,
    "tajikistan": 143,
    "bahrain": 145,
    "reunion": 146,
    "zambia": 147,
    "armenia": 148,
    "burkinafaso": 152,
    "gabon": 154,
    "albania": 155,
    "uruguay": 156,
    "mauritius": 157,
    "bhutan": 158,
    "maldives": 159,
    "turkmenistan": 161,
    "frenchguiana": 162,
    "finland": 163,
    "saintlucia": 164,
    "luxembourg": 165,
    "saintvincentandthegrenadines": 166,
    "antiguaandbarbuda": 169,
    "switzerland": 173,
    "norway": 174,
    "australia": 175,
    "aruba": 179,
    "anguilla": 181,
    "northmacedonia": 183,
    "newcaledonia": 185,
    "capeverde": 186
  }
  